{"categoryGeneratedIndex":{"title":"Practical Guides & How-to Articles","description":"Step-by-step guides for common tasks and real-world scenarios. Learn best practices, discover tips and tricks, and follow detailed walkthroughs that help you accomplish specific goals with Docusaurus.","slug":"/guides","permalink":"/hiddendirectory-cantaccess/docs/guides","sidebar":"tutorialSidebar","navigation":{"previous":{"title":"API Overview","permalink":"/hiddendirectory-cantaccess/docs/api-reference/overview"},"next":{"title":"Guides & How-to Articles","permalink":"/hiddendirectory-cantaccess/docs/guides/overview"}}}}